{
  "metadata": {
    "__rokb_email_type": "kvk",
    "__rokb_battle_type": "rally",
    "__rokb_battle_data_sender_skipped_participants": 0,
    "__rokb_battle_data_opponents_skipped_participants": 0,
    "email_id": "70657339176503384525",
    "email_time": 1765033845629453,
    "email_receiver": "player_2295184",
    "server_id": 15763
  },
  "battle_trends": {
    "sampling": [
      {
        "count": 372349,
        "tick": 1301721
      },
      {
        "count": 362704,
        "tick": 1301731
      }
    ],
    "events": []
  },
  "battle_data": {
    "sender": {
      "player_id": 2295184,
      "player_name": "Sttuu",
      "app_uid": "2147252",
      "camp": 4,
      "kingdom": 2473,
      "alliance": {
        "tag": "~73D",
        "name": "Divine Clankers 73"
      },
      "avatar_url": "https://plat-fau-global.lilithgame.com/p/astc/IM/10043/0/2147252/2025-10-25/59990794073A8BB2967675D4C4EB9479_250x250.jpg",
      "frame_url": "http://imimg.lilithcdn.com/roc/img_ProfileBg220x220_a.png",
      "commanders": {
        "primary": {
          "id": 185,
          "level": 60,
          "equipment": "{1:20002_200:1,2:20005_160:1,3:20026_223:11,4:20029_163:14,5:20032_224:11,6:20034_226:3,7:20118_152:1,8:20040_175:1}",
          "formation": 1,
          "star": 6,
          "awakened": true,
          "armaments": [
            {
              "slot": 1,
              "buffs": "3001_0.032000;4001_0.027000;5001_0.025000",
              "inscriptions": "113"
            },
            {
              "slot": 4,
              "buffs": "3001_0.019000;4001_0.017000;5001_0.022000",
              "inscriptions": "-1"
            },
            {
              "slot": 3,
              "buffs": "6001_0.033000;4001_0.015000;5001_0.026000",
              "inscriptions": "304"
            },
            {
              "slot": 2,
              "buffs": "3001_0.031000;4001_0.017000;5001_0.015000",
              "inscriptions": "210;214"
            }
          ]
        },
        "secondary": {
          "id": 98,
          "level": 60,
          "equipment": "{}",
          "star": 6,
          "awakened": true
        }
      },
      "castle": {
        "pos": {
          "x": 623,
          "y": 578
        },
        "level": 25
      },
      "participants": [
        {
          "player_id": 2295184,
          "player_name": "Sttuu",
          "alliance": {
            "tag": "~73D"
          },
          "commanders": {
            "primary": {
              "id": 185,
              "level": 60
            },
            "secondary": {
              "id": 98,
              "level": 60
            }
          }
        }
      ]
    },
    "opponents": [
      {
        "player_id": 45985429,
        "player_name": "ᴾʰˣFuRiouSs",
        "app_uid": "38406629",
        "camp": 5,
        "kingdom": 2283,
        "alliance": {
          "tag": "RA83",
          "name": "Rise From the Ashes"
        },
        "avatar_url": "https://plat-fau-global.lilithgame.com/p/astc/IM/10043/0/38406629/2025-11-28/2D572B83F584003FCBF905CCC42F674A_250x250.jpg",
        "frame_url": "http://imimg.lilithcdn.com/roc/img_AvatarFrame_50.png",
        "commanders": {
          "primary": {
            "id": 103,
            "level": 60,
            "equipment": "{1:20001_804:35,2:20004_799:35,3:20009_803:35,4:20028_771:32,5:20033_763:35,6:20012_765:32,7:20037_801:35,8:20040_786:35}",
            "formation": 13,
            "star": 6,
            "awakened": true,
            "armaments": [
              {
                "slot": 1,
                "buffs": "3002_0.025000;4002_0.033000;5002_0.031000",
                "inscriptions": "13101"
              },
              {
                "slot": 4,
                "buffs": "3002_0.022000;4002_0.033000;5002_0.027000",
                "inscriptions": "13402"
              },
              {
                "slot": 3,
                "buffs": "3002_0.025000;4002_0.031000;5002_0.026000",
                "inscriptions": "13301"
              },
              {
                "slot": 2,
                "buffs": "3002_0.021000;4002_0.027000;5002_0.023000",
                "inscriptions": "13201"
              }
            ]
          },
          "secondary": {
            "id": 539,
            "level": 60,
            "equipment": "{}",
            "star": 6,
            "awakened": true
          }
        },
        "castle": {
          "pos": {
            "x": 555,
            "y": 557
          },
          "level": 25
        },
        "participants": [
          {
            "player_id": 155757187,
            "player_name": "MoreBeer",
            "alliance": {
              "tag": "RA83"
            },
            "commanders": {
              "primary": {
                "id": 7,
                "level": 60
              },
              "secondary": {
                "id": 61,
                "level": 60
              }
            }
          },
          {
            "player_id": 52624545,
            "player_name": "Shy Falcon",
            "alliance": {
              "tag": "RA83"
            },
            "commanders": {
              "primary": {
                "id": 182,
                "level": 60
              },
              "secondary": {
                "id": 148,
                "level": 60
              }
            }
          },
          {
            "player_id": 64012553,
            "player_name": "TwistzLG",
            "alliance": {
              "tag": "RA83"
            },
            "commanders": {
              "primary": {
                "id": 540,
                "level": 60
              },
              "secondary": {
                "id": 575,
                "level": 40
              }
            }
          },
          {
            "player_id": 164772007,
            "player_name": "ᴾʰˣBoo",
            "alliance": {
              "tag": "RA83"
            },
            "commanders": {
              "primary": {
                "id": 148,
                "level": 60
              }
            }
          },
          {
            "player_id": 164783378,
            "player_name": "ᴾʰˣ NIXPRO",
            "alliance": {
              "tag": "RA83"
            },
            "commanders": {
              "primary": {
                "id": 182,
                "level": 60
              }
            }
          },
          {
            "player_id": 15415503,
            "player_name": "Яツalbator dark",
            "alliance": {
              "tag": "RA83"
            },
            "commanders": {
              "primary": {
                "id": 179,
                "level": 60
              },
              "secondary": {
                "id": 161,
                "level": 60
              }
            }
          }
        ]
      }
    ]
  }
}