[
  {
    "addition": "",
    "attachments": [],
    "body": {
      "content": {
        "Attacks": {
          "186643701": {
            "Bts": 906332,
            "CIdt": {
              "AId": 0,
              "AName": "",
              "Abbr": "",
              "Avatar": "",
              "CAHAH": [],
              "CASS": {
                "Ban": false,
                "ENABLE": false
              },
              "CId": 186643701,
              "COSId": 0,
              "CT": 1,
              "CTK": "-2_1769789566_85",
              "CastleLevel": 0,
              "CastlePos": {
                "X": 3748.8755,
                "Y": 4147.133
              },
              "CtId": 1605906,
              "DisappearTick": 914117,
              "HAw": false,
              "HAw2": false,
              "HEq": "{}",
              "HId": 85,
              "HId2": 0,
              "HLv": 34,
              "HLv2": 0,
              "HSS": [
                1,
                {
                  "SkillId": 110,
                  "SkillLevel": 5
                }
              ],
              "HSt": 5,
              "HSt2": 0,
              "HTE": 0,
              "HTJ": 0,
              "HTJ2": 0,
              "Idt": "186643701",
              "IfAI": 0,
              "IsAuto": 0,
              "KVKMorale": {
                "CampX": 0,
                "CampY": 0,
                "Distance": 0,
                "Morale": 0
              },
              "NpcBType": 1,
              "NpcType": 34,
              "PId": -2,
              "PName": "",
              "SerSeason": "",
              "Titan": {
                "BattleId": "",
                "Pioneer": false,
                "Round": 0,
                "TeamId": 0
              }
            },
            "Damage": {
              "AddCnt": 0,
              "AtkPower": -518,
              "BadHurt": 76,
              "BadReduceCnt": 0,
              "Cnt": 270640,
              "Contribute": 0,
              "DeadReduceCnt": 0,
              "Death": 0,
              "Gt": 0,
              "GtMax": 0,
              "Healing": 0,
              "Hurt": 3261,
              "HurtCntEnd": 116050,
              "InitMax": 388000,
              "KillScore": 0,
              "Max": 363575,
              "Power": -532,
              "RetreatCnt": 0,
              "SkillPower": -14,
              "UnitStifleBadHurtReduceCnt": 0,
              "WarExploits": 0
            },
            "Def": 2,
            "Ets": 906369,
            "Kill": {
              "AddCnt": 0,
              "AtkPower": -224176,
              "BadHurt": 0,
              "BadReduceCnt": 0,
              "Cnt": 0,
              "Contribute": 0,
              "DeadReduceCnt": 0,
              "Death": 165000,
              "Gt": 0,
              "GtMax": 0,
              "Healing": 0,
              "Hurt": 0,
              "HurtCntEnd": 0,
              "InitMax": 165000,
              "KillScore": 0,
              "Max": 165000,
              "Power": -660000,
              "RetreatCnt": 0,
              "SkillPower": -435824,
              "UnitStifleBadHurtReduceCnt": 0,
              "WarExploits": 0
            },
            "NpcAtkExp": 4760,
            "NpcKillLoot": [
              1,
              {
                "SubType": 143,
                "Type": 2,
                "Value": 59
              },
              2,
              {
                "SubType": 71,
                "Type": 2,
                "Value": 8
              },
              3,
              {
                "SubType": 128,
                "Type": 2,
                "Value": 34
              }
            ],
            "OTs": {
              "1605906": {
                "Abbr": "",
                "HId": 85,
                "HId2": 0,
                "HLv": 34,
                "HLv2": 0,
                "PId": -2,
                "PName": ""
              }
            },
            "OppositeDu": {
              "DuCnt": 0,
              "DuMax": 0
            },
            "OpsKvkModBuffIds": [],
            "Pos": {
              "X": 3754.0183,
              "Y": 4147.5947
            },
            "ReportShowType": 0,
            "RewardLimited": false,
            "SelfDu": {
              "DuCnt": 0,
              "DuMax": 0
            },
            "SelfKvkModBuffIds": [],
            "StatShowType": 1,
            "Tick": 38,
            "TickStart": 906332
          },
          "189076501": {
            "Bts": 906321,
            "CIdt": {
              "AId": 0,
              "AName": "",
              "Abbr": "",
              "Avatar": "",
              "CAHAH": [],
              "CASS": {
                "Ban": false,
                "ENABLE": false
              },
              "CId": 189076501,
              "COSId": 0,
              "CT": 1,
              "CTK": "-2_1769801604_204",
              "CastleLevel": 0,
              "CastlePos": {
                "X": 3754.0183,
                "Y": 4152.67
              },
              "CtId": 1626958,
              "DisappearTick": 990254,
              "HAw": false,
              "HAw2": false,
              "HEq": "{}",
              "HId": 204,
              "HId2": 0,
              "HLv": 60,
              "HLv2": 0,
              "HSS": [
                1,
                {
                  "SkillId": 127,
                  "SkillLevel": 5
                }
              ],
              "HSt": 6,
              "HSt2": 0,
              "HTE": 0,
              "HTJ": 0,
              "HTJ2": 0,
              "Idt": "189076501",
              "IfAI": 0,
              "IsAuto": 0,
              "IsFort": true,
              "KVKMorale": {
                "CampX": 0,
                "CampY": 0,
                "Distance": 0,
                "Morale": 0
              },
              "NpcBType": 2,
              "NpcType": 110,
              "PId": -2,
              "PName": "",
              "SerSeason": "",
              "Titan": {
                "BattleId": "",
                "Pioneer": false,
                "Round": 0,
                "TeamId": 0
              }
            },
            "Damage": {
              "AddCnt": 0,
              "AtkPower": -25184,
              "BadHurt": 3898,
              "BadReduceCnt": 0,
              "Cnt": 41294,
              "Contribute": 0,
              "DeadReduceCnt": 0,
              "Death": 0,
              "Gt": 0,
              "GtMax": 0,
              "Healing": 0,
              "Hurt": 339471,
              "HurtCntEnd": 342732,
              "InitMax": 388000,
              "KillScore": 0,
              "Max": 388000,
              "Power": -29068,
              "RetreatCnt": 0,
              "SkillPower": -3884,
              "UnitStifleBadHurtReduceCnt": 0,
              "WarExploits": 0
            },
            "Def": 2,
            "Ets": 906557,
            "Kill": {
              "AddCnt": 0,
              "AtkPower": -2234508,
              "BadHurt": 0,
              "BadReduceCnt": 0,
              "Cnt": 0,
              "Contribute": 0,
              "DeadReduceCnt": 0,
              "Death": 2000000,
              "Gt": 0,
              "GtMax": 0,
              "Healing": 0,
              "Hurt": 0,
              "HurtCntEnd": 0,
              "InitMax": 2000000,
              "KillScore": 0,
              "Max": 2000000,
              "Power": -8000000,
              "RetreatCnt": 0,
              "SkillPower": -5765492,
              "UnitStifleBadHurtReduceCnt": 0,
              "WarExploits": 0
            },
            "NpcAtkExp": 0,
            "OTs": {
              "1626958": {
                "Abbr": "",
                "HId": 204,
                "HId2": 0,
                "HLv": 60,
                "HLv2": 0,
                "PId": -2,
                "PName": ""
              }
            },
            "OppositeDu": {
              "DuCnt": 0,
              "DuMax": 0
            },
            "OpsKvkModBuffIds": [],
            "Pos": {
              "X": 3754.5127,
              "Y": 4146.154
            },
            "ReportShowType": 0,
            "RewardLimited": false,
            "SelfDu": {
              "DuCnt": 0,
              "DuMax": 0
            },
            "SelfKvkModBuffIds": [],
            "StatShowType": 1,
            "Tick": 237,
            "TickStart": 906321
          }
        },
        "Btk": 906321,
        "Bts": 1769802676,
        "DataOmit": false,
        "Ets": 1769802911,
        "Events": [],
        "GsId": 1804,
        "Id": 6301574,
        "LLScriptSchema": 320,
        "LoadSource": "oss",
        "Role": "gsmp",
        "RoomId": 0,
        "STs": {
          "1628577": {
            "Abbr": "SO4L",
            "HId": 540,
            "HId2": 575,
            "HLv": 60,
            "HLv2": 60,
            "PId": 71738515,
            "PName": "Grigvar"
          },
          "1628608": {
            "Abbr": "SO4L",
            "HId": 61,
            "HId2": 15,
            "HLv": 40,
            "HLv2": 40,
            "PId": 159922529,
            "PName": "GメKnight 2"
          }
        },
        "Samples": [
          1,
          {
            "Cnt": 388000,
            "T": 906321
          },
          2,
          {
            "Cnt": 363575,
            "T": 906332
          },
          3,
          {
            "Cnt": 270640,
            "T": 906369
          },
          4,
          {
            "Cnt": 41294,
            "T": 906557
          }
        ],
        "Schema": 10,
        "SelfChar": {
          "AId": 4805441,
          "AName": "魂社会SoulReapers",
          "Abbr": "SO4L",
          "AppUid": "32624247",
          "Avatar": "{\"avatarFrame\":\"http://imimg.lilithcdn.com/roc/img_AvatarFrame_189.png\",\"avatar\":\"https://plat-fau-global.lilithgame.com/p/astc/IM/10043/0/32624247/2026-01-15/1822754B851EA438ECFE0FF4994C2FA6_250x250.jpg\"}",
          "CAHAH": [],
          "CASS": {
            "Ban": false,
            "ENABLE": false
          },
          "CId": 189336301,
          "COSId": 1804,
          "CT": 1,
          "CTK": "71738515_1769802374_540_575_SquareRally",
          "CastleLevel": 25,
          "CastlePos": {
            "X": 3815.7598,
            "Y": 3977.461
          },
          "CtId": 1628577,
          "HAw": true,
          "HAw2": true,
          "HEq": "{1:20007_400:2,2:20008_260:2,3:20009_381:2,4:20028_378:2,5:20033_382:2,6:20012_383:2,7:20040_394:1,8:20037_338:1}",
          "HEq2": "{1:20001_380:2,2:20004_379:32,3:20009_190:2,4:20028_265:33,5:20033_261:32,6:20012_266:3,7:20040_264:1,8:20037_398:31}",
          "HFMs": 13,
          "HFMs2": 13,
          "HId": 540,
          "HId2": 575,
          "HLv": 60,
          "HLv2": 60,
          "HSS": [
            1,
            {
              "SkillId": 389,
              "SkillLevel": 5
            },
            2,
            {
              "SkillId": 1735,
              "SkillLevel": 5
            },
            3,
            {
              "SkillId": 1736,
              "SkillLevel": 5
            },
            4,
            {
              "SkillId": 1737,
              "SkillLevel": 5
            },
            5,
            {
              "SkillId": 1738,
              "SkillLevel": 1
            }
          ],
          "HSS2": [
            1,
            {
              "SkillId": 1790,
              "SkillLevel": 5
            },
            2,
            {
              "SkillId": 1789,
              "SkillLevel": 5
            },
            3,
            {
              "SkillId": 411,
              "SkillLevel": 5
            },
            4,
            {
              "SkillId": 1787,
              "SkillLevel": 5
            }
          ],
          "HSt": 6,
          "HSt2": 6,
          "HTE": -1,
          "HTJ": 0,
          "HTJ2": 0,
          "HWBs": {
            "1": {
              "Affix": "107",
              "Buffs": "3002_0.019000;4002_0.027000;10002_0.018000",
              "Id": "75113011_18860"
            },
            "2": {
              "Affix": "13202",
              "Buffs": "3002_0.026000;4002_0.033000;10002_0.015000",
              "Id": "75213010_16122"
            },
            "3": {
              "Affix": "13302",
              "Buffs": "3002_0.028000;4002_0.017000;5002_0.018000",
              "Id": "75313011_18861"
            },
            "4": {
              "Affix": "407;418",
              "Buffs": "6002_0.022000;4002_0.020000;5002_0.020000",
              "Id": "75413012_18004"
            }
          },
          "HWBs2": {
            "1": "75113012_8250",
            "2": "75213011_11529",
            "3": "75313010_11530",
            "4": "75413011_18189"
          },
          "Idt": "189336301",
          "IfAI": 0,
          "IsAuto": 0,
          "IsRally": true,
          "KVKMorale": {
            "CampX": 0,
            "CampY": 0,
            "Distance": 0,
            "Morale": 0
          },
          "PId": 71738515,
          "PName": "Grigvar",
          "PkgNameNew": "com.lilithgames.rok.pc.int",
          "SerSeason": "100",
          "Titan": {
            "BattleId": "",
            "Pioneer": false,
            "Round": 0,
            "TeamId": 0
          },
          "Udid": "489044729533721131"
        },
        "TickSkip": 100
      }
    },
    "box": "Report",
    "flaglist": [],
    "holdTag": 0,
    "id": "33830971176980291131",
    "mailScene": 0,
    "preMailId": "",
    "receiver": "player_71738515",
    "receiverInfo": {
      "Abbr": "",
      "Name": ""
    },
    "reportMerge": 0,
    "sender": "system",
    "senderInfo": {
      "Abbr": "",
      "Name": "system"
    },
    "senderTradeTime": 0,
    "serverId": 1804,
    "starMark": 0,
    "time": 1769802911843205,
    "title": "",
    "type": "Battle",
    "unread": false
  }
]